_youtokentome_cython.cpython-37m-x86_64-linux-gnu.so
youtokentome-1.0.6.dist-info/top_level.txt
youtokentome-1.0.6.dist-info/RECORD
youtokentome-1.0.6.dist-info/METADATA
youtokentome-1.0.6.dist-info/entry_points.txt
youtokentome-1.0.6.dist-info/WHEEL
youtokentome/yttm_cli.py
youtokentome/__init__.py
youtokentome/youtokentome.py
