Metadata-Version: 2.1
Name: youtokentome
Version: 1.0.6
Summary: Unsupervised text tokenizer focused on computational efficiency
Home-page: https://github.com/vkcom/youtokentome
Author: Ivan Belonogov
License: MIT
Platform: UNKNOWN
Classifier: License :: OSI Approved :: MIT License
Classifier: Programming Language :: Python
Classifier: Programming Language :: Python :: 3
Classifier: Programming Language :: Python :: 3.5
Classifier: Programming Language :: Python :: 3.6
Classifier: Programming Language :: Python :: 3.7
Classifier: Programming Language :: Python :: 3.8
Classifier: Programming Language :: Python :: Implementation :: CPython
Classifier: Programming Language :: Cython
Classifier: Programming Language :: C++
Requires-Python: >=3.5.0
Requires-Dist: Click (>=7.0)
